LICENSE
MANIFEST.in
README.rst
setup.cfg
setup.py
vpnauth/__init__.py
vpnauth/config.py
vpnauth/core.py
vpnauth/daemon.py
vpnauth/dbutil.py
vpnauth/errors.py
vpnauth/notif.py
vpnauth/ovpnstatus.py
vpnauth/server.py
vpnauth/util.py
vpnauth.egg-info/PKG-INFO
vpnauth.egg-info/SOURCES.txt
vpnauth.egg-info/dependency_links.txt
vpnauth.egg-info/entry_points.txt
vpnauth.egg-info/requires.txt
vpnauth.egg-info/top_level.txt