Metadata-Version: 1.1
Name: vpnauth
Version: 0.0.13
Summary: Enigma Bridge VPN authenticator
Home-page: https://github.com/EnigmaBridge/VpnAuthServer
Author: Enigma Bridge
Author-email: info@enigmabridge.com
License: MIT License
